demesdraw/__init__.py
demesdraw/__main__.py
demesdraw/_version.py
demesdraw/py.typed
demesdraw/size_history.py
demesdraw/tubes.py
demesdraw/utils.py
demesdraw-0.4.0.dist-info/LICENSE
demesdraw-0.4.0.dist-info/METADATA
demesdraw-0.4.0.dist-info/WHEEL
demesdraw-0.4.0.dist-info/entry_points.txt
demesdraw-0.4.0.dist-info/top_level.txt
demesdraw-0.4.0.dist-info/RECORD
