Metadata-Version: 2.1
Name: demesdraw
Version: 0.4.0
Summary: drawing tools for Demes demographic models
Home-page: https://github.com/grahamgower/demesdraw
Author: Graham Gower
License: ISC
Project-URL: Documentation, https://grahamgower.github.io/demesdraw/
Project-URL: Source Code, https://github.com/grahamgower/demesdraw
Project-URL: Bug Tracker, https://github.com/grahamgower/demesdraw/issues
Classifier: Development Status :: 4 - Beta
Classifier: License :: OSI Approved :: ISC License (ISCL)
Classifier: Operating System :: OS Independent
Classifier: Intended Audience :: Science/Research
Classifier: Programming Language :: Python :: 3
Classifier: Programming Language :: Python :: 3.7
Classifier: Programming Language :: Python :: 3.8
Classifier: Programming Language :: Python :: 3.9
Classifier: Programming Language :: Python :: 3.10
Classifier: Topic :: Scientific/Engineering
Classifier: Topic :: Scientific/Engineering :: Bio-Informatics
Classifier: Topic :: Scientific/Engineering :: Visualization
Requires-Python: >=3.7
License-File: LICENSE
Requires-Dist: demes (>=0.2.0)
Requires-Dist: matplotlib (>=3.3.1)
Requires-Dist: numpy (>=1.20.0)
Requires-Dist: scipy
